BBox.h
INSTALL
LICENSE
README
configure.py
ftgl.sip
setup.py
sippy_ftgl.egg-info/PKG-INFO
sippy_ftgl.egg-info/SOURCES.txt
sippy_ftgl.egg-info/dependency_links.txt
sippy_ftgl.egg-info/top_level.txt