Metadata-Version: 1.0
Name: sippy-ftgl
Version: 0.1.0
Summary: Python binding for FTGL using SIP
Home-page: http://code.google.com/p/sippy-ftgl/
Author: michael j pan
Author-email: mikepan@gmail.com
License: New BSD
Keywords: ftgl SIP
Platform: All
